dacot/__init__.py
dacot/data.py
dacot/run.py
dacot/utils.py
dacot/version.py
dacot/transform/__init__.py
dacot/transform/flux.py
dacot-2.0.0.dist-info/AUTHORS
dacot-2.0.0.dist-info/METADATA
dacot-2.0.0.dist-info/WHEEL
dacot-2.0.0.dist-info/entry_points.txt
dacot-2.0.0.dist-info/pbr.json
dacot-2.0.0.dist-info/top_level.txt
dacot-2.0.0.dist-info/RECORD
