Metadata-Version: 2.1
Name: dacot
Version: 2.0.0
Summary: DataCOVID Transformer
Home-page: https://github.com/ifca/dacot
Author: Alvaro Lopez Garcia
Author-email: aloga@ifca.unican.es
License: UNKNOWN
Platform: UNKNOWN
Classifier: Development Status :: 5 - Production/Stable
Classifier: Environment :: Console
Classifier: Environment :: Web Environment
Classifier: Intended Audience :: Developers
Classifier: Intended Audience :: Information Technology
Classifier: Intended Audience :: Science/Research
Classifier: License :: OSI Approved :: Apache Software License
Classifier: Operating System :: OS Independent
Classifier: Programming Language :: Python
Classifier: Programming Language :: Python :: 3
Classifier: Topic :: Internet :: WWW/HTTP
Requires-Dist: pbr (!=2.1.0,>=2.0.0)
Requires-Dist: pandas
Requires-Dist: requests
